nextcord/ext/events/__init__.py
nextcord/ext/events/_events.py
nextcord/ext/events/member_kick.py
nextcord/ext/events/mixins.py
nextcord/ext/events/utils.py
nextcord_ext_events-0.1.0a0.dist-info/LICENSE
nextcord_ext_events-0.1.0a0.dist-info/METADATA
nextcord_ext_events-0.1.0a0.dist-info/WHEEL
nextcord_ext_events-0.1.0a0.dist-info/top_level.txt
nextcord_ext_events-0.1.0a0.dist-info/RECORD
